CHANGES.txt
CREDITS.txt
HISTORY.txt
LICENSE.txt
README.txt
TODO.txt
setup.py
Products/__init__.py
Products/listen/__init__.py
Products/listen/config.py
Products/listen/configure.zcml
Products/listen/i18n.py
Products/listen/migrations.py
Products/listen/overrides.zcml
Products/listen/permissions.py
Products/listen/permissions.zcml
Products/listen/profiles.zcml
Products/listen/version.txt
Products/listen/browser/__init__.py
Products/listen/browser/archive_date_messages.pt
Products/listen/browser/archive_date_view.pt
Products/listen/browser/archive_forum_view.pt
Products/listen/browser/archive_thread_messages.pt
Products/listen/browser/base.py
Products/listen/browser/configure.zcml
Products/listen/browser/contentviews.py
Products/listen/browser/export.pt
Products/listen/browser/export.py
Products/listen/browser/forum_message_view.pt
Products/listen/browser/import.pt
Products/listen/browser/import.py
Products/listen/browser/import_export.pt
Products/listen/browser/import_export.py
Products/listen/browser/lookup_view.pt
Products/listen/browser/mail_archive_views.py
Products/listen/browser/mail_message_views.py
Products/listen/browser/mailinglist_view.pt
Products/listen/browser/mailinglist_views.py
Products/listen/browser/manage_membership.pt
Products/listen/browser/manage_membership.py
Products/listen/browser/message_macros.pt
Products/listen/browser/message_reply_view.pt
Products/listen/browser/migration.pt
Products/listen/browser/moderation.pt
Products/listen/browser/moderation.py
Products/listen/browser/new_topic_view.pt
Products/listen/browser/obfuscation.js
Products/listen/browser/overrides.zcml
Products/listen/browser/search.pt
Products/listen/browser/search_debug_view.pt
Products/listen/browser/threaded_message.pt
Products/listen/browser/listwidget/__init__.py
Products/listen/browser/listwidget/configure.zcml
Products/listen/browser/listwidget/listoperations.js
Products/listen/browser/listwidget/widget.pt
Products/listen/browser/listwidget/widget.py
opencore_listen.egg-info/PKG-INFO
opencore_listen.egg-info/SOURCES.txt
opencore_listen.egg-info/dependency_links.txt
opencore_listen.egg-info/entry_points.txt
opencore_listen.egg-info/namespace_packages.txt
opencore_listen.egg-info/not-zip-safe
opencore_listen.egg-info/requires.txt
opencore_listen.egg-info/top_level.txt