Metadata-Version: 1.0
Name: opencore-listen
Version: 0.8.0
Summary: listen is a mailing list product for Plone
Home-page: http://trac.socialplanning.org/listen
Author: Robert Marianski, Alec Mitchell, Chris Abraham, Rob Miller, Ethan Jucovy
Author-email: listen-dev at lists.coactivate.org
License: GPL
Platform: UNKNOWN
